PythonWebUI/__init__.py
PythonWebUI/core.py
PythonWebUI/main.py
PythonWebUI/HTMLBulider/__init__.py
PythonWebUI/HTMLBulider/builder.py
PythonWebUI/HTMLNodes/DoubleMarker.py
PythonWebUI/HTMLNodes/SelfDefine.py
PythonWebUI/HTMLNodes/SingleMarker.py
PythonWebUI/HTMLNodes/__init__.py
pythonwebui-0.1.1.dist-info/licenses/LICENSE
pythonwebui-0.1.1.dist-info/METADATA
pythonwebui-0.1.1.dist-info/WHEEL
pythonwebui-0.1.1.dist-info/top_level.txt
pythonwebui-0.1.1.dist-info/RECORD
