Metadata-Version: 2.4
Name: PythonWebUI
Version: 0.1.1
Summary: Rapid HTML Construction with Python.
Home-page: https://github.com/kwokzl/PythonWebUI
Author: Zonglin Guo
Requires-Python: >=3.6
License-File: LICENSE
Dynamic: author
Dynamic: description
Dynamic: description-content-type
Dynamic: home-page
Dynamic: license-file
Dynamic: requires-python
Dynamic: summary
